{"$ambrosia":"aero:interactive:9417ac60-5f60-11ea-8e69-affb2224d7e8:*","$id":"02724640-44e0-11ed-8032-cad59af08419","$workspaceId":"7fff47c0-44d6-11ed-bcef-d5307f42495c","$projectId":"86cb0040-44df-11ed-8442-dbcbc27803ca","annotations":[],"configSchemaVersion":"/pluginGenericSchema/v1","config":{"stage":{"sections":[{"rows":[{"columns":[{"stageElements":[{"type":"stage-element-text","value":{"object":"value","document":{"object":"document","data":{},"nodes":[{"object":"block","type":"heading-two","ref":"909899ae-633f-4c3c-aa7e-0487b6403245","nodes":[{"object":"text","text":"The Returns of Individual Stocks","marks":[]}],"data":{}}]}},"config":{"cssClass":""},"ref":"6c77caa2-baf9-43b6-93c5-bb82c837c9f8"},{"type":"stage-element-text","value":{"object":"value","document":{"object":"document","data":{},"nodes":[{"object":"block","type":"paragraph","ref":"ab76f097-687a-4b1b-b867-9301f1094cd5","nodes":[{"object":"inline","type":"reference-link","ref":"07a94fed-c84f-4ca4-bb40-00fd5607b7a1","nodes":[{"object":"text","text":"Figure 11.6","marks":[]}],"data":{"reference":"427a11e0-44e1-11ed-8442-dbcbc27803ca"}},{"object":"text","text":" suggests the following simple model of the risk premium: Investments with higher volatility should have a higher risk premium and therefore higher returns. Indeed, looking at the dotted line in ","marks":[]},{"object":"inline","type":"reference-link","ref":"28af5f26-caff-42e7-92e5-bf97e5cb0ce9","nodes":[{"object":"text","text":"Figure 11.6","marks":[]}],"data":{"reference":"427a11e0-44e1-11ed-8442-dbcbc27803ca"}},{"object":"text","text":", it is tempting to conclude that all investments should lie on or near this line—that is, expected return should rise proportionately with volatility. This conclusion appears to be approximately true for the large portfolios we have looked at so far. Is it correct? Does it apply to individual stocks?","marks":[]}],"data":{}}]}},"config":{"cssClass":""},"ref":"1423ef2b-d2a4-4508-a1ba-0c25c50d46a5"},{"type":"stage-element-text","value":{"object":"value","document":{"object":"document","data":{},"nodes":[{"object":"block","type":"paragraph","ref":"fa31fd89-fc1d-41bc-a8af-5f33ba21632e","nodes":[{"object":"text","text":"Actually, the answer to both questions is no. There is no clear relationship between volatility and returns for individual stocks. ","marks":[]},{"object":"inline","type":"reference-link","ref":"1222cfe7-7e12-493f-b22b-fc3f7570afa7","nodes":[{"object":"text","text":"Figure 11.7","marks":[]}],"data":{"reference":"4908fe90-44e1-11ed-8442-dbcbc27803ca"}},{"object":"text","text":" shows that, if we look at the volatility and return of individual stocks, we do not see any clear relationship between them. Each point represents the volatility and average return from investing in the ","marks":[]},{"object":"text","text":"N","marks":[{"type":"italic"}]},{"object":"text","text":"th largest stock traded in the United States (updated annually) for ","marks":[]},{"object":"inline","type":"mathml-expression","data":{"mathML":"<math alttext=\"\" class=\"inlineequation\" display=\"inline\" altimg=\"../images/s1altmath_808.png\" altimg-height=\"15\" altimg-width=\"46\"><mrow><mi>N</mi><mo>=</mo><mn>1</mn></mrow></math>","display":"inline","alt":"upper N equals 1","svg":"<svg style=\"vertical-align: -0.186ex\" xmlns=\"http://www.w3.org/2000/svg\" width=\"6.157ex\" height=\"1.731ex\" role=\"img\" focusable=\"false\" viewBox=\"0 -683 2721.6 765\" xmlns:xlink=\"http://www.w3.org/1999/xlink\" aria-hidden=\"true\"><defs><path id=\"MJX-1017-TEX-I-1D441\" d=\"M234 637Q231 637 226 637Q201 637 196 638T191 649Q191 676 202 682Q204 683 299 683Q376 683 387 683T401 677Q612 181 616 168L670 381Q723 592 723 606Q723 633 659 637Q635 637 635 648Q635 650 637 660Q641 676 643 679T653 683Q656 683 684 682T767 680Q817 680 843 681T873 682Q888 682 888 672Q888 650 880 642Q878 637 858 637Q787 633 769 597L620 7Q618 0 599 0Q585 0 582 2Q579 5 453 305L326 604L261 344Q196 88 196 79Q201 46 268 46H278Q284 41 284 38T282 19Q278 6 272 0H259Q228 2 151 2Q123 2 100 2T63 2T46 1Q31 1 31 10Q31 14 34 26T39 40Q41 46 62 46Q130 49 150 85Q154 91 221 362L289 634Q287 635 234 637Z\"></path><path id=\"MJX-1017-TEX-N-3D\" d=\"M56 347Q56 360 70 367H707Q722 359 722 347Q722 336 708 328L390 327H72Q56 332 56 347ZM56 153Q56 168 72 173H708Q722 163 722 153Q722 140 707 133H70Q56 140 56 153Z\"></path><path id=\"MJX-1017-TEX-N-31\" d=\"M213 578L200 573Q186 568 160 563T102 556H83V602H102Q149 604 189 617T245 641T273 663Q275 666 285 666Q294 666 302 660V361L303 61Q310 54 315 52T339 48T401 46H427V0H416Q395 3 257 3Q121 3 100 0H88V46H114Q136 46 152 46T177 47T193 50T201 52T207 57T213 61V578Z\"></path></defs><g stroke=\"currentColor\" fill=\"currentColor\" stroke-width=\"0\" transform=\"matrix(1 0 0 -1 0 0)\"><g data-mml-node=\"math\" class=\" inlineequation\"><g data-mml-node=\"mrow\" data-semantic-type=\"relseq\" data-semantic-role=\"equality\" data-semantic-id=\"3\" data-semantic-children=\"0,2\" data-semantic-content=\"1\" data-semantic-speech=\"upper N equals 1\"><g data-mml-node=\"mi\" data-semantic-type=\"identifier\" data-semantic-role=\"latinletter\" data-semantic-font=\"italic\" data-semantic-annotation=\"clearspeak:simple\" data-semantic-id=\"0\" data-semantic-parent=\"3\" data-semantic-speech=\"upper N\"><use xlink:href=\"#MJX-1017-TEX-I-1D441\"></use></g><g data-mml-node=\"mo\" data-semantic-type=\"relation\" data-semantic-role=\"equality\" data-semantic-id=\"1\" data-semantic-parent=\"3\" data-semantic-operator=\"relseq,=\" data-semantic-speech=\"equals\" transform=\"translate(1165.8, 0)\"><use xlink:href=\"#MJX-1017-TEX-N-3D\"></use></g><g data-mml-node=\"mn\" data-semantic-type=\"number\" data-semantic-role=\"integer\" data-semantic-font=\"normal\" data-semantic-annotation=\"clearspeak:simple\" data-semantic-id=\"2\" data-semantic-parent=\"3\" data-semantic-speech=\"1\" transform=\"translate(2221.6, 0)\"><use xlink:href=\"#MJX-1017-TEX-N-31\"></use></g></g></g></g></svg>"},"ref":"8505e43b-f74c-462f-a1cf-1bfd8d807cb2","nodes":[]},{"object":"text","text":" to 500. Although it will take more work to establish the relation between risk and return for individual stocks, the following is true:","marks":[]}],"data":{}}]}},"config":{"cssClass":" math-expression"},"ref":"7e01776b-bef3-46bc-b6bc-6685ed2cabe4"},{"type":"stage-element-text","value":{"object":"value","document":{"object":"document","data":{},"nodes":[{"object":"block","type":"ordered-list","data":{"listOptionType":"1","startValue":1},"ref":"31f2604f-b026-4b07-b0f6-d361fb98d6a2","nodes":[{"object":"block","type":"list-item","data":{"direction":"auto"},"ref":"2da1d5ed-10c4-48a3-9f84-2a956b31cb57","nodes":[{"object":"block","type":"paragraph","ref":"f8ca6502-c26a-4cab-a3a6-a59f35d4fb3a","nodes":[{"object":"text","text":"There is a relationship between size and risk—on average larger stocks have lower volatility than smaller stocks.","marks":[]}],"data":{}}]},{"object":"block","type":"list-item","data":{"direction":"auto"},"ref":"52f17d5c-df8a-44d1-986b-dd2a3179da33","nodes":[{"object":"block","type":"paragraph","ref":"a486e31a-614b-4aa7-b361-ee87f9b25ad5","nodes":[{"object":"text","text":"Even the largest stocks are typically more volatile than a portfolio of large stocks, such as the S&P 500.","marks":[]}],"data":{}}]},{"object":"block","type":"list-item","data":{"direction":"auto"},"ref":"8bdf9a68-2749-4521-b867-b491907b712a","nodes":[{"object":"block","type":"paragraph","ref":"15740ff5-130d-4cba-98d3-1ef49d048d4e","nodes":[{"object":"text","text":"All individual stocks have lower returns and/or higher risk than the portfolios in ","marks":[]},{"object":"inline","type":"reference-link","ref":"2b9850da-7784-4202-b02c-7412a2852841","nodes":[{"object":"text","text":"Figure 11.6","marks":[]}],"data":{"reference":"427a11e0-44e1-11ed-8442-dbcbc27803ca"}},{"object":"text","text":".","marks":[]}],"data":{}}]}]}]}},"config":{"cssClass":""},"ref":"6bcaf7e9-10f5-443b-ab8c-24657a98b432"},{"type":"stage-element-image","config":{"url":{"$ambrosia":"aero:asset:upload","urn":"urn:aero:b27fb3b0-44e0-11ed-9423-b5340f85eced","asset":{"urn":"urn:aero:b27fb3b0-44e0-11ed-9423-b5340f85eced","asset":{"assetProvider":"ALFRESCO","id":"b27fb3b0-44e0-11ed-9423-b5340f85eced","assetMediaType":"image","assetVisibility":"GLOBAL","ownerId":"e88133a0-8dc4-11eb-964e-4d7e264c9958","subscriptionId":"f0afd4d0-d2ff-11ea-9998-d57e1e28aca1","alfrescoId":"caef082a-06bc-4b40-bb0d-6f8514c424fa","name":"FG_11_007.jpg","version":"2.0","lastModifiedDate":1664998751,"lastSyncDate":1665085925},"source":{"small":{"width":492,"url":"https://assets-bronte-qaint.pearson.com/b27fb3b0-44e0-11ed-9423-b5340f85eced/small/40667298d5ef303133f8d2e1be65c4bf.jpeg","height":300},"original":{"width":985,"url":"https://assets-bronte-qaint.pearson.com/b27fb3b0-44e0-11ed-9423-b5340f85eced/medium/40667298d5ef303133f8d2e1be65c4bf.jpeg","height":600},"medium":{"width":985,"url":"https://assets-bronte-qaint.pearson.com/b27fb3b0-44e0-11ed-9423-b5340f85eced/medium/40667298d5ef303133f8d2e1be65c4bf.jpeg","height":600},"thumb":{"width":246,"url":"https://assets-bronte-qaint.pearson.com/b27fb3b0-44e0-11ed-9423-b5340f85eced/thumb/40667298d5ef303133f8d2e1be65c4bf.jpeg","height":150}},"metadata":{"altText":"","workURN":"","caption":"<p>Unlike the case for large portfolios, there is no precise relationship between volatility and average return for individual stocks. Individual stocks have higher volatility and lower average returns than the relationship shown for large portfolios. (Annual data from 1926&#x2013;2014.)</p>","alfrescoPath":"bronte-e2e-testing-qaint/documentLibrary/BV E2E Test/[10-05-2022] Berk","originalAssetName":"FG_11_007.jpg","longDesc":"","height":"488"}}},"alt":"","caption":"<p>Unlike the case for large portfolios, there is no precise relationship between volatility and average return for individual stocks. Individual stocks have higher volatility and lower average returns than the relationship shown for large portfolios. (Annual data from 1926&#x2013;2014.)</p>","layout":{"captionPosition":"Below"},"credit":"<p><em>Source</em>: CRSP.</p>","activityLabel":"Figure 11.7","activityTitle":"Historical Volatility and Return for 500 Individual Stocks, Ranked Annually by Size"},"height":488,"ref":"cca8f888-d380-4d3d-a8e3-f2e0f49cf23b"},{"type":"stage-element-text","value":{"object":"value","document":{"object":"document","data":{},"nodes":[{"object":"block","type":"paragraph","ref":"08fc71b5-4f0d-41b8-b09d-528b1da81bac","nodes":[{"object":"text","text":"Thus, while volatility (standard deviation) seems to be a reasonable measure of risk when evaluating a large portfolio, the volatility of an individual security doesn’t explain the size of its average return","marks":[{"type":"italic"}]},{"object":"text","text":". What are we to make of this? Why wouldn’t investors demand a higher return from stocks with a higher volatility? And how is it that the S&P 500, a portfolio of 500 large stocks, is so much less risky than almost all of the 500 stocks individually? To answer these questions, we need to think more carefully about how to measure risk for an investor.","marks":[]}],"data":{}}]}},"config":{"cssClass":""},"ref":"c599140a-ef9d-45f7-a137-ce3e9af6bcd0"}]}]}]},{"cssClass":"aside-group Sidebar_1Aside","rows":[{"columns":[{"stageElements":[{"type":"stage-element-text","value":{"object":"value","document":{"object":"document","data":{},"nodes":[{"object":"block","type":"heading-two","ref":"e47b4d1b-d237-4793-8996-86df3b97ab96","nodes":[{"object":"text","text":"Concept Check","marks":[]}],"data":{}}]}},"config":{"cssClass":""},"ref":"9d731b1c-6a75-47c4-9252-2c77821c3728"},{"type":"stage-element-text","value":{"object":"value","document":{"object":"document","data":{},"nodes":[{"object":"block","type":"ordered-list","data":{"listOptionType":"1","startValue":5},"ref":"2a73e1bd-11c2-4e5d-aebd-f5230ef96f12","nodes":[{"object":"block","type":"list-item","data":{"direction":"auto"},"ref":"26c1a95c-1a33-4a0b-8061-e2b36b600387","nodes":[{"object":"block","type":"paragraph","ref":"07da786c-6402-495e-afb8-b9c68336a7a5","nodes":[{"object":"text","text":"What is the relation between risk and return for large portfolios? How are individual stocks different?","marks":[]}],"data":{}}]},{"object":"block","type":"list-item","data":{"direction":"auto"},"ref":"9c09592a-3aa9-4e00-8e7a-401a9894dd56","nodes":[{"object":"block","type":"paragraph","ref":"c6ce2ff4-2d0d-4294-839a-4ca6fa0c1765","nodes":[{"object":"text","text":"Do portfolios or the stocks in the portfolios tend to have the lower volatility?","marks":[]}],"data":{}}]}]}]}},"config":{"cssClass":""},"ref":"80a9f401-7819-4c4c-a23d-f106a3d9b878"}]}]}]}]},"screenType":"","transitions":{"enter":{"animation":"","duration":0,"easing":"","customKeyframes":""},"exit":{"animation":"","duration":0,"easing":"","customKeyframes":""}},"lockElements":false,"learnerCurrentAttempt":1,"footer":{"buttonText":"Next","buttonIcon":"Arrow","showFooter":false,"showHistoryNavButtons":false,"previewFooter":false,"position":"Fixed to screen bottom","footerComponent":{"showFooterDropArea":"hide","width":100,"footerComponentsAlignment":"right"}},"styles":{"background":{},"stage":{"maxWidth":940,"background":"rgba(255, 255, 255, 1)","responsive":true,"padding":{"vertical":60,"horizontal":60},"border":{"color":"rgba(224, 224, 224, 1)","radius":0,"width":0}},"elements":{"padding":{"vertical":10,"horizontal":10}},"footer":{"buttonColor":"rgba(0, 115, 202, 1)","textColor":"rgba(0, 0, 0, 0.7)","backgroundColor":"rgba(255, 255, 255, 1)","padding":10,"corners":4,"border":"none","shadow":"0 -1px 4px 0 rgba(0,0,0,0.06), 0 0 12px 2px rgba(0,0,0,0.1)"},"feedback":{"width":320,"textColor":"rgba(0, 0, 0, 0.7)","backgroundColor":"rgba(255, 255, 255, 1)","corners":4,"border":"none","shadow":"0 5px 47px 10px rgba(0,0,0,0.15), 0 10px 20px 2px rgba(0,0,0,0.1), 0 7px 8px 0 rgba(0,0,0,0.1)"}},"title":"The Returns of Individual Stocks"},"assets":[{"urn":"urn:aero:b27fb3b0-44e0-11ed-9423-b5340f85eced","asset":{"assetProvider":"ALFRESCO","id":"b27fb3b0-44e0-11ed-9423-b5340f85eced","assetMediaType":"image","assetVisibility":"GLOBAL","ownerId":"e88133a0-8dc4-11eb-964e-4d7e264c9958","subscriptionId":"f0afd4d0-d2ff-11ea-9998-d57e1e28aca1","alfrescoId":"caef082a-06bc-4b40-bb0d-6f8514c424fa","name":"FG_11_007.jpg","version":"2.0","lastModifiedDate":1664998751,"lastSyncDate":1665085925},"source":{"small":{"width":492,"url":"https://assets-bronte-qaint.pearson.com/b27fb3b0-44e0-11ed-9423-b5340f85eced/small/40667298d5ef303133f8d2e1be65c4bf.jpeg","height":300},"original":{"width":985,"url":"https://assets-bronte-qaint.pearson.com/b27fb3b0-44e0-11ed-9423-b5340f85eced/medium/40667298d5ef303133f8d2e1be65c4bf.jpeg","height":600},"medium":{"width":985,"url":"https://assets-bronte-qaint.pearson.com/b27fb3b0-44e0-11ed-9423-b5340f85eced/medium/40667298d5ef303133f8d2e1be65c4bf.jpeg","height":600},"thumb":{"width":246,"url":"https://assets-bronte-qaint.pearson.com/b27fb3b0-44e0-11ed-9423-b5340f85eced/thumb/40667298d5ef303133f8d2e1be65c4bf.jpeg","height":150}},"metadata":{"altText":"","workURN":"","caption":"<p>Unlike the case for large portfolios, there is no precise relationship between volatility and average return for individual stocks. Individual stocks have higher volatility and lower average returns than the relationship shown for large portfolios. (Annual data from 1926&#x2013;2014.)</p>","alfrescoPath":"bronte-e2e-testing-qaint/documentLibrary/BV E2E Test/[10-05-2022] Berk","originalAssetName":"FG_11_007.jpg","longDesc":"","height":"488"}}],"scenarios":[],"pluginPayload":{"pluginRepositoryPath":"https://plugin-repository-bronte-qaint.pearson.com/9417ac60-5f60-11ea-8e69-affb2224d7e8/0.15.209/ac43ee4c0eda05e9718fa83a5aed4cff.zip","summary":{"pluginId":"9417ac60-5f60-11ea-8e69-affb2224d7e8","name":"Screen","description":"A screen of a lesson","type":"screen","latestVersion":"0.15.209","subscriptionId":"f0afd4d0-d2ff-11ea-9998-d57e1e28aca1","createdAt":"Fri, 6 Mar 2020 04:11:39 GMT","updatedAt":"Tue, 13 Dec 2022 22:07:46 GMT","tags":[],"publishMode":"DEFAULT"}},"activityThemeIconLibraries":[]}