{"$ambrosia":"aero:interactive:9417ac60-5f60-11ea-8e69-affb2224d7e8:*","$id":"0e716930-44e0-11ed-828f-d2d4e3aad6c9","$workspaceId":"7fff47c0-44d6-11ed-bcef-d5307f42495c","$projectId":"86cb0040-44df-11ed-8442-dbcbc27803ca","annotations":[],"configSchemaVersion":"/pluginGenericSchema/v1","config":{"stage":{"sections":[{"rowsAreFullWidth":false,"backgroundImageUrl":"","rows":[{"columns":[{"stageElements":[{"type":"stage-element-text","value":{"object":"value","document":{"object":"document","data":{},"nodes":[{"object":"block","type":"heading-one","ref":"0d6d6b7e-295a-48be-a596-767ccc68a6ee","nodes":[{"object":"text","text":"Part 7: Integrative Case","marks":[]}],"data":{}}]}},"config":{"cssClass":""},"ref":"8f6da323-190a-49ea-b449-f5f73f1bdd29"}]}]},{"columns":[{"stageElements":[{"type":"stage-element-text","value":{"object":"value","document":{"object":"document","data":{},"nodes":[{"object":"block","type":"paragraph","ref":"c716a9ad-fc98-4e34-be8f-5c52d142c2b4","nodes":[{"object":"text","text":"This case draws on material from ","marks":[{"type":"italic"}]},{"object":"inline","type":"reference-link","ref":"b4106601-c5c7-4267-8cb3-42d1e8aaab47","nodes":[{"object":"text","text":"Chapters 18","marks":[{"type":"italic"}]}],"data":{"reference":"770db1f0-44e1-11ed-8442-dbcbc27803ca"}},{"object":"text","text":"–","marks":[{"type":"italic"}]},{"object":"inline","type":"reference-link","ref":"ca2749a7-86e5-4c9a-8e17-77bbeac0ab41","nodes":[{"object":"text","text":"20","marks":[{"type":"italic"}]}],"data":{"reference":"805f4110-44e1-11ed-8442-dbcbc27803ca"}},{"object":"text","text":". See MyLab Finance for the data in ","marks":[{"type":"italic"}]},{"object":"inline","type":"reference-link","ref":"c35baf92-c4c7-4863-82e2-8528952c0975","nodes":[{"object":"text","text":"Tables 1","marks":[{"type":"italic"}]}],"data":{"reference":"b0cbccb0-44e1-11ed-8442-dbcbc27803ca"}},{"object":"text","text":", ","marks":[{"type":"italic"}]},{"object":"inline","type":"reference-link","ref":"3f84ae0d-f5f2-4bb6-b7d2-80b2a74c0842","nodes":[{"object":"text","text":"2","marks":[{"type":"italic"}]}],"data":{"reference":"b0d73e60-44e1-11ed-8442-dbcbc27803ca"}},{"object":"text","text":", ","marks":[{"type":"italic"}]},{"object":"inline","type":"reference-link","ref":"1d742a8a-a53e-4de5-a883-19a0b58f0721","nodes":[{"object":"text","text":"3","marks":[{"type":"italic"}]}],"data":{"reference":"b42027d0-44e1-11ed-8442-dbcbc27803ca"}},{"object":"text","text":", and ","marks":[{"type":"italic"}]},{"object":"inline","type":"reference-link","ref":"86d14960-348e-47a0-819d-c6c877b67909","nodes":[{"object":"text","text":"4","marks":[{"type":"italic"}]}],"data":{"reference":"b90dc090-44e1-11ed-8442-dbcbc27803ca"}},{"object":"text","text":" and the spreadsheet referenced in the case questions","marks":[{"type":"italic"}]},{"object":"text","text":".","marks":[]}],"data":{}}]}},"config":{"cssClass":""},"ref":"405fb63c-fe5f-488a-b566-3d69c843899d"}]}]},{"columns":[{"stageElements":[{"type":"stage-element-text","value":{"object":"value","document":{"object":"document","data":{},"nodes":[{"object":"block","type":"paragraph","ref":"0af88f43-f225-427f-9e6b-4bcc88b291a3","nodes":[{"object":"text","text":"Idexo Corporation is a privately held designer and manufacturer of licensed college apparel in Cincinnati, Ohio. In late 2019, after several years of lackluster performance, the firm’s owner and founder, Rebecca Ferris, returned from retirement to replace the current CEO, reinvigorate the firm, and plan for its eventual sale or possible IPO. She has hired you to assist with developing the firm’s financial plan for the next five years.","marks":[]}],"data":{}}]}},"config":{"cssClass":""},"ref":"f07da1ea-c1ce-4f34-8be1-59dcfb7f0359"}]}]},{"columns":[{"stageElements":[{"type":"stage-element-text","value":{"object":"value","document":{"object":"document","data":{},"nodes":[{"object":"block","type":"paragraph","ref":"525d6a14-97d7-4b54-8e18-b72155629c55","nodes":[{"object":"text","text":"In 2019, Idexo had total assets of about $103 million and annual sales of $100 million (see ","marks":[]},{"object":"inline","type":"reference-link","ref":"68872f5c-af6a-46a0-be4e-0e7044b632ce","nodes":[{"object":"text","text":"Table 1","marks":[]}],"data":{"reference":"b0cbccb0-44e1-11ed-8442-dbcbc27803ca"}},{"object":"text","text":"). The firm was profitable, with expected 2019 earnings of more than $9 million, for a net profit margin of 9.1%.","marks":[]},{"data":{"ref":"ea1eafba-262d-4fb0-be6f-4e6ca4b1be84","stage":{"ref":"ee5eb9ee-4fe8-4755-a10b-e7cb01ab3a6d","sections":[{"ref":"0a3586c6-6d91-493e-bf40-dfeec6f4c3ed","rows":[{"ref":"ac599683-5456-4bbd-a5b5-a86514edf85a","columns":[{"ref":"be2e4c52-9fec-4b8f-85e8-2485755607d2","stageElements":[{"ref":"b313c1a2-ac7f-4ffc-b1c7-881a1b5d2e36","type":"stage-element-text","value":{"object":"value","document":{"object":"document","data":{},"nodes":[{"object":"block","type":"button","ref":"c5e4b53f-4fba-422d-b665-dc5d5e3ba9a3","nodes":[{"object":"block","type":"paragraph","ref":"83e0a94c-0cae-4b2a-969d-2e2f437c5ff2","nodes":[{"object":"text","text":"See ","marks":[]},{"object":"inline","type":"reference-link","ref":"5088f101-7b3b-4bc7-913c-e9710013c242","nodes":[{"object":"text","text":"Table 1","marks":[]}],"data":{"reference":"b0cbccb0-44e1-11ed-8442-dbcbc27803ca"}},{"object":"text","text":" for further projected income and balance sheet information for 2019.","marks":[]}],"data":{}}],"data":{}}]}}}]}]}]}]}},"nodes":[{"object":"text","text":"1","marks":[]}],"object":"inline","type":"footnote","ref":"be8df46e-6862-40cc-86f3-ee129fb9eaab"},{"object":"text","text":" However, revenue growth has slowed dramatically in recent years and the firm’s net profit margin has actually been declining. Ferris is convinced the firm can do better. After only several weeks at the helm, she has already identified a number of potential improvements to drive the firm’s future growth.","marks":[]}],"data":{}}]}},"config":{"cssClass":""},"ref":"9bb50066-bf29-4fbb-a778-16a279057853"}]}]}]}]},"screenType":"","transitions":{"enter":{"animation":"","duration":0,"easing":"","customKeyframes":""},"exit":{"animation":"","duration":0,"easing":"","customKeyframes":""}},"lockElements":false,"learnerCurrentAttempt":1,"footer":{"buttonText":"Next","buttonIcon":"Arrow","showFooter":false,"showHistoryNavButtons":false,"previewFooter":false,"position":"Fixed to screen bottom","footerComponent":{"showFooterDropArea":"hide","width":100,"footerComponentsAlignment":"right"}},"styles":{"background":{},"stage":{"maxWidth":940,"background":"rgba(255, 255, 255, 1)","responsive":true,"padding":{"vertical":60,"horizontal":60},"border":{"color":"rgba(224, 224, 224, 1)","radius":0,"width":0}},"elements":{"padding":{"vertical":10,"horizontal":10}},"footer":{"buttonColor":"rgba(0, 115, 202, 1)","textColor":"rgba(0, 0, 0, 0.7)","backgroundColor":"rgba(255, 255, 255, 1)","padding":10,"corners":4,"border":"none","shadow":"0 -1px 4px 0 rgba(0,0,0,0.06), 0 0 12px 2px rgba(0,0,0,0.1)"},"feedback":{"width":320,"textColor":"rgba(0, 0, 0, 0.7)","backgroundColor":"rgba(255, 255, 255, 1)","corners":4,"border":"none","shadow":"0 5px 47px 10px rgba(0,0,0,0.15), 0 10px 20px 2px rgba(0,0,0,0.1), 0 7px 8px 0 rgba(0,0,0,0.1)"}},"title":"Part 7: Integrative Case"},"assets":[],"scenarios":[],"pluginPayload":{"pluginRepositoryPath":"https://plugin-repository-bronte-qaint.pearson.com/9417ac60-5f60-11ea-8e69-affb2224d7e8/0.15.209/ac43ee4c0eda05e9718fa83a5aed4cff.zip","summary":{"pluginId":"9417ac60-5f60-11ea-8e69-affb2224d7e8","name":"Screen","description":"A screen of a lesson","type":"screen","latestVersion":"0.15.209","subscriptionId":"f0afd4d0-d2ff-11ea-9998-d57e1e28aca1","createdAt":"Fri, 6 Mar 2020 04:11:39 GMT","updatedAt":"Tue, 13 Dec 2022 22:07:46 GMT","tags":[],"publishMode":"DEFAULT"}},"activityThemeIconLibraries":[]}