{"$ambrosia":"aero:interactive:9417ac60-5f60-11ea-8e69-affb2224d7e8:*","$id":"ed646990-44df-11ed-85c2-8b050ec738c2","$workspaceId":"7fff47c0-44d6-11ed-bcef-d5307f42495c","$projectId":"86cb0040-44df-11ed-8442-dbcbc27803ca","annotations":[],"configSchemaVersion":"/pluginGenericSchema/v1","config":{"stage":{"sections":[{"cssClass":"chapterIntro","rows":[{"columns":[{"stageElements":[{"type":"stage-element-image","config":{"url":{"$ambrosia":"aero:asset:upload","urn":"urn:aero:4a8b2730-44e0-11ed-bcef-d5307f42495c","asset":{"urn":"urn:aero:4a8b2730-44e0-11ed-bcef-d5307f42495c","asset":{"assetProvider":"ALFRESCO","id":"4a8b2730-44e0-11ed-bcef-d5307f42495c","assetMediaType":"image","assetVisibility":"GLOBAL","ownerId":"e88133a0-8dc4-11eb-964e-4d7e264c9958","subscriptionId":"f0afd4d0-d2ff-11ea-9998-d57e1e28aca1","alfrescoId":"bd40e926-40aa-4eed-a111-ec1bc2057d04","name":"Generic_ChapterIntro_Blue.png","version":"2.0","lastModifiedDate":1664998387,"lastSyncDate":1665085940},"source":{"small":{"width":463,"url":"https://assets-bronte-qaint.pearson.com/4a8b2730-44e0-11ed-bcef-d5307f42495c/small/eb48c237847833402531fabe9d971ea4.png","height":300},"original":{"width":925,"url":"https://assets-bronte-qaint.pearson.com/4a8b2730-44e0-11ed-bcef-d5307f42495c/medium/eb48c237847833402531fabe9d971ea4.png","height":600},"medium":{"width":925,"url":"https://assets-bronte-qaint.pearson.com/4a8b2730-44e0-11ed-bcef-d5307f42495c/medium/eb48c237847833402531fabe9d971ea4.png","height":600},"thumb":{"width":231,"url":"https://assets-bronte-qaint.pearson.com/4a8b2730-44e0-11ed-bcef-d5307f42495c/thumb/eb48c237847833402531fabe9d971ea4.png","height":150}},"metadata":{"altText":"","workURN":"","caption":"","alfrescoPath":"bronte-e2e-testing-qaint/documentLibrary/BV E2E Test/[10-05-2022] Berk","originalAssetName":"Generic_ChapterIntro_Blue.png","longDesc":"","height":"519"}}},"alt":"","caption":"","layout":{"captionPosition":"Below"},"credit":"","activityLabel":"","activityTitle":""},"height":519,"ref":"4040fa88-ea5f-46de-b13f-6e1300b2399d"},{"type":"stage-element-text","value":{"object":"value","document":{"object":"document","data":{},"nodes":[{"object":"block","type":"heading-one","nodes":[{"object":"inline","type":"styledText","data":{"styledText":"chapterNumber","id":"3"},"nodes":[{"object":"text","text":"4","marks":[]}]}],"data":{}}]}},"config":{"cssClass":"chapterNumber"},"ref":"fc18365c-6c42-420f-8f9c-ec1363551cb3"},{"type":"stage-element-text","value":{"object":"value","document":{"object":"document","data":{},"nodes":[{"object":"block","type":"heading-one","ref":"e9de4247-9264-4f98-8d99-0ecbb9e52dcd","nodes":[{"object":"text","text":"Time Value of Money: Valuing Cash Flow Streams","marks":[]}],"data":{}}]}},"config":{"cssClass":"chapterTitle"},"ref":"91761df7-32ec-4107-a8f1-0894934c5d2d"}]}]}]},{"cssClass":"objectiveset","rows":[{"columns":[{"stageElements":[{"type":"stage-element-text","value":{"object":"value","document":{"object":"document","data":{},"nodes":[{"object":"block","type":"heading-two","ref":"6a91b48e-dea4-4fd1-8275-206a77ef93fd","nodes":[{"object":"text","text":"Learning Objectives","marks":[]}],"data":{}}]}},"config":{"cssClass":""},"ref":"0f968dc6-76ba-4cb8-a064-f3432149a953"},{"type":"stage-element-text","value":{"object":"value","document":{"object":"document","data":{},"nodes":[{"object":"block","type":"unordered-list","data":{"listOptionType":"","startValue":""},"ref":"efcce03b-2c2e-4eb7-a792-345e062d49d9","nodes":[{"object":"block","type":"list-item","data":{"direction":"auto"},"ref":"9a3bac20-b285-491d-b584-a02df873e123","nodes":[{"object":"block","type":"paragraph","ref":"61668341-1b01-4a56-8e5e-0727a4f77167","nodes":[{"object":"text","text":"• Value a series of many cash flows","marks":[]}],"data":{}}]},{"object":"block","type":"list-item","data":{"direction":"auto"},"ref":"bcceeb1b-ffc6-40f7-bd1b-268d2cfb4745","nodes":[{"object":"block","type":"paragraph","ref":"a6b23d20-4283-42a4-b107-eb83acf1dd07","nodes":[{"object":"text","text":"• Value a perpetual series of regular cash flows called a ","marks":[]},{"object":"text","text":"perpetuity","marks":[{"type":"italic"}]}],"data":{}}]},{"object":"block","type":"list-item","data":{"direction":"auto"},"ref":"d336556d-1b2f-447e-9e32-c8467e4926d6","nodes":[{"object":"block","type":"paragraph","ref":"85f6ff62-c2d7-4ceb-83f2-364d5b009e5f","nodes":[{"object":"text","text":"• Value a common set of regular cash flows called an ","marks":[]},{"object":"text","text":"annuity","marks":[{"type":"italic"}]}],"data":{}}]},{"object":"block","type":"list-item","data":{"direction":"auto"},"ref":"68a576b5-069d-4920-a7ea-18a692a60001","nodes":[{"object":"block","type":"paragraph","ref":"282a5ec3-91ee-4d05-a715-947dfc82bbcf","nodes":[{"object":"text","text":"• Value both perpetuities and annuities when the cash flows grow at a constant rate","marks":[]}],"data":{}}]},{"object":"block","type":"list-item","data":{"direction":"auto"},"ref":"fd3aae0f-7477-41ce-983c-0da587c3ccbb","nodes":[{"object":"block","type":"paragraph","ref":"078ddea2-494b-4ba1-b793-8a6e52260fa0","nodes":[{"object":"text","text":"• Compute the number of periods, cash flow, or rate of return of a loan or investment","marks":[]}],"data":{}}]},{"object":"block","type":"list-item","data":{"direction":"auto"},"ref":"8a39382b-c5d8-4084-9c08-bc4145fcfe83","nodes":[{"object":"block","type":"paragraph","ref":"42038beb-2a09-42dc-bdbe-78864615c14d","nodes":[{"object":"text","text":"• Value cash flow streams with non-annual payments","marks":[]}],"data":{}}]}]}]}},"config":{"cssClass":"ul_none"},"ref":"19aa8f67-fbb2-43ad-add3-0216e23740ef"}]}]}]}]},"screenType":"","transitions":{"enter":{"animation":"","duration":0,"easing":"","customKeyframes":""},"exit":{"animation":"","duration":0,"easing":"","customKeyframes":""}},"lockElements":false,"learnerCurrentAttempt":1,"footer":{"buttonText":"Next","buttonIcon":"Arrow","showFooter":false,"showHistoryNavButtons":false,"previewFooter":false,"position":"Fixed to screen bottom","footerComponent":{"showFooterDropArea":"hide","width":100,"footerComponentsAlignment":"right"}},"styles":{"background":{},"stage":{"maxWidth":940,"background":"rgba(255, 255, 255, 1)","responsive":true,"padding":{"vertical":60,"horizontal":60},"border":{"color":"rgba(224, 224, 224, 1)","radius":0,"width":0}},"elements":{"padding":{"vertical":10,"horizontal":10}},"footer":{"buttonColor":"rgba(0, 115, 202, 1)","textColor":"rgba(0, 0, 0, 0.7)","backgroundColor":"rgba(255, 255, 255, 1)","padding":10,"corners":4,"border":"none","shadow":"0 -1px 4px 0 rgba(0,0,0,0.06), 0 0 12px 2px rgba(0,0,0,0.1)"},"feedback":{"width":320,"textColor":"rgba(0, 0, 0, 0.7)","backgroundColor":"rgba(255, 255, 255, 1)","corners":4,"border":"none","shadow":"0 5px 47px 10px rgba(0,0,0,0.15), 0 10px 20px 2px rgba(0,0,0,0.1), 0 7px 8px 0 rgba(0,0,0,0.1)"}},"title":"4"},"assets":[{"urn":"urn:aero:4a8b2730-44e0-11ed-bcef-d5307f42495c","asset":{"assetProvider":"ALFRESCO","id":"4a8b2730-44e0-11ed-bcef-d5307f42495c","assetMediaType":"image","assetVisibility":"GLOBAL","ownerId":"e88133a0-8dc4-11eb-964e-4d7e264c9958","subscriptionId":"f0afd4d0-d2ff-11ea-9998-d57e1e28aca1","alfrescoId":"bd40e926-40aa-4eed-a111-ec1bc2057d04","name":"Generic_ChapterIntro_Blue.png","version":"2.0","lastModifiedDate":1664998387,"lastSyncDate":1665085940},"source":{"small":{"width":463,"url":"https://assets-bronte-qaint.pearson.com/4a8b2730-44e0-11ed-bcef-d5307f42495c/small/eb48c237847833402531fabe9d971ea4.png","height":300},"original":{"width":925,"url":"https://assets-bronte-qaint.pearson.com/4a8b2730-44e0-11ed-bcef-d5307f42495c/medium/eb48c237847833402531fabe9d971ea4.png","height":600},"medium":{"width":925,"url":"https://assets-bronte-qaint.pearson.com/4a8b2730-44e0-11ed-bcef-d5307f42495c/medium/eb48c237847833402531fabe9d971ea4.png","height":600},"thumb":{"width":231,"url":"https://assets-bronte-qaint.pearson.com/4a8b2730-44e0-11ed-bcef-d5307f42495c/thumb/eb48c237847833402531fabe9d971ea4.png","height":150}},"metadata":{"altText":"","workURN":"","caption":"","alfrescoPath":"bronte-e2e-testing-qaint/documentLibrary/BV E2E Test/[10-05-2022] Berk","originalAssetName":"Generic_ChapterIntro_Blue.png","longDesc":"","height":"519"}}],"scenarios":[],"pluginPayload":{"pluginRepositoryPath":"https://plugin-repository-bronte-qaint.pearson.com/9417ac60-5f60-11ea-8e69-affb2224d7e8/0.15.209/ac43ee4c0eda05e9718fa83a5aed4cff.zip","summary":{"pluginId":"9417ac60-5f60-11ea-8e69-affb2224d7e8","name":"Screen","description":"A screen of a lesson","type":"screen","latestVersion":"0.15.209","subscriptionId":"f0afd4d0-d2ff-11ea-9998-d57e1e28aca1","createdAt":"Fri, 6 Mar 2020 04:11:39 GMT","updatedAt":"Tue, 13 Dec 2022 22:07:46 GMT","tags":[],"publishMode":"DEFAULT"}},"activityThemeIconLibraries":[]}